finage/__init__.py
finage/client.py
finage-0.1.5.dist-info/LICENSE
finage-0.1.5.dist-info/METADATA
finage-0.1.5.dist-info/WHEEL
finage-0.1.5.dist-info/top_level.txt
finage-0.1.5.dist-info/RECORD
