Metadata-Version: 2.1
Name: finage
Version: 0.1.5
Summary: Package to utilize Finage REST API
Home-page: https://github.com/athompson1991/finage
Author: Alex Thompson
Author-email: alexthompson_1991@yahoo.com
Maintainer: Alex Thompson
Maintainer-email: alexthompson_1991@yahoo.com
License: MIT
Keywords: Finage,finance,stocks,forex
Platform: UNKNOWN
Classifier: Programming Language :: Python :: 3.9
License-File: LICENSE
Requires-Dist: requests
